tensorflow_image_models/AlexNet.py
tensorflow_image_models/CspNet.py
tensorflow_image_models/DPN.py
tensorflow_image_models/DenseNet.py
tensorflow_image_models/DenseNet121.py
tensorflow_image_models/DenseNet169.py
tensorflow_image_models/DenseNet201.py
tensorflow_image_models/EfficientNet.py
tensorflow_image_models/Inception.py
tensorflow_image_models/InceptionResNetV1.py
tensorflow_image_models/InceptionResNetV2.py
tensorflow_image_models/InceptionV3.py
tensorflow_image_models/InceptionV4.py
tensorflow_image_models/LeNet.py
tensorflow_image_models/MobileNet.py
tensorflow_image_models/MobileNetV1.py
tensorflow_image_models/MobileNetV2.py
tensorflow_image_models/ResNeXt.py
tensorflow_image_models/ResNet.py
tensorflow_image_models/ResNet101.py
tensorflow_image_models/ResNet152.py
tensorflow_image_models/ResNet18.py
tensorflow_image_models/ResNet34.py
tensorflow_image_models/ResNet50.py
tensorflow_image_models/ShufflenetV2.py
tensorflow_image_models/VGG.py
tensorflow_image_models/VGG16.py
tensorflow_image_models/VGG19.py
tensorflow_image_models/VisionTransformer.py
tensorflow_image_models/VoVNet.py
tensorflow_image_models/Xception.py
tensorflow_image_models/__init__.py
tensorflow_image_models/importLayers.py
tensorflow_image_models/main.py
tensorflow_image_models-0.0.11.dist-info/METADATA
tensorflow_image_models-0.0.11.dist-info/WHEEL
tensorflow_image_models-0.0.11.dist-info/top_level.txt
tensorflow_image_models-0.0.11.dist-info/RECORD
