Metadata-Version: 2.1
Name: tensorflow-image-models
Version: 0.0.11
Summary: Tensorflow image models
Author: DEEPOLOGY LAB
Author-email: alaa.m.elmor@gmail.com
Classifier: Programming Language :: Python :: 3
Classifier: License :: OSI Approved :: MIT License
Classifier: Operating System :: OS Independent
Requires-Python: >=3.6
